pydoc_utils.py
pydoc_utils-1.0.1.dist-info/DESCRIPTION.rst
pydoc_utils-1.0.1.dist-info/METADATA
pydoc_utils-1.0.1.dist-info/RECORD
pydoc_utils-1.0.1.dist-info/WHEEL
pydoc_utils-1.0.1.dist-info/metadata.json
pydoc_utils-1.0.1.dist-info/top_level.txt
