Metadata-Version: 2.0
Name: pydoc-utils
Version: 1.0.1
Summary: A pydoc utility modules. It prints all modules, classes, methods and functions in stdout.
Home-page: https://github.com/co-dh/pydoc_utils
Author: Hao Deng
Author-email: UNKNOWN
License: UNKNOWN
Platform: UNKNOWN
